{
  "date": "2026-02-25",
  "country": "us",
  "mediaType": "apps",
  "feedType": "top-paid",
  "limit": 100,
  "genre": "6000",
  "source": "https://itunes.apple.com/us/rss/toppaidapplications/limit=100/genre=6000/json",
  "total": 97,
  "items": [
    {
      "date": "2026-02-25",
      "rank": 1,
      "id": "294934058",
      "name": "HotSchedules",
      "artistName": "HotSchedules",
      "kind": "Business",
      "releaseDate": "2008-10-30T22:30:52-07:00",
      "artworkUrl100": "https://is1-ssl.mzstatic.com/image/thumb/Purple221/v4/78/f8/72/78f872a3-4e39-789e-343f-099c6cb2a592/AppIcon-1x_U007emarketing-0-8-0-85-220-0.png/100x100bb.png",
      "url": ""
    },
    {
      "date": "2026-02-25",
      "rank": 2,
      "id": "601159497",
      "name": "ecMobile",
      "artistName": "e-Courier, Inc.",
      "kind": "Business",
      "releaseDate": "2013-02-15T16:22:27-07:00",
      "artworkUrl100": "https://is1-ssl.mzstatic.com/image/thumb/Purple221/v4/d3/dc/07/d3dc078f-23c2-6a04-5c9c-7f3df8c67a36/AppIcon-1x_U007emarketing-0-8-0-85-220-0.png/100x100bb.png",
      "url": ""
    },
    {
      "date": "2026-02-25",
      "rank": 3,
      "id": "342548956",
      "name": "TurboScan™ Pro: PDF scanner",
      "artistName": "Piksoft Inc.",
      "kind": "Business",
      "releaseDate": "2009-12-07T09:46:12-07:00",
      "artworkUrl100": "https://is1-ssl.mzstatic.com/image/thumb/Purple221/v4/98/02/fc/9802fc47-b5c2-4f87-4b4c-05e18ad5822d/AppIcon-0-0-1x_U007epad-0-1-0-0-85-220.png/100x100bb.png",
      "url": ""
    },
    {
      "date": "2026-02-25",
      "rank": 4,
      "id": "364876095",
      "name": "Jump Desktop (RDP, VNC, Fluid)",
      "artistName": "Phase Five Systems",
      "kind": "Business",
      "releaseDate": "2010-04-01T11:37:48-07:00",
      "artworkUrl100": "https://is1-ssl.mzstatic.com/image/thumb/Purple126/v4/25/78/9b/25789b0f-a94a-e60d-85d8-61dd8acf6ce4/AppIcon-0-0-1x_U007emarketing-0-0-0-10-0-0-sRGB-0-0-0-GLES2_U002c0-512MB-85-220-0-0.png/100x100bb.png",
      "url": ""
    },
    {
      "date": "2026-02-25",
      "rank": 5,
      "id": "1309752471",
      "name": "Superpowers by SYPartners",
      "artistName": "SYPartners LLC",
      "kind": "Business",
      "releaseDate": "2018-01-11T09:35:11-07:00",
      "artworkUrl100": "https://is1-ssl.mzstatic.com/image/thumb/Purple128/v4/58/6b/e5/586be5dd-fe10-0283-25b3-485f0be27c26/AppIcon-1x_U007emarketing-85-220-6.png/100x100bb.png",
      "url": ""
    },
    {
      "date": "2026-02-25",
      "rank": 6,
      "id": "936694037",
      "name": "Voice Recorder - Audio Record",
      "artistName": "LiveBird Technologies Private Limited",
      "kind": "Business",
      "releaseDate": "2014-11-20T06:26:18-07:00",
      "artworkUrl100": "https://is1-ssl.mzstatic.com/image/thumb/Purple221/v4/3c/a2/2b/3ca22b95-3cfd-1030-78e9-366259ada74c/AppIcon-0-0-1x_U007emarketing-0-8-0-85-220.png/100x100bb.png",
      "url": ""
    },
    {
      "date": "2026-02-25",
      "rank": 7,
      "id": "577499909",
      "name": "TapeACall Pro: Call Recorder",
      "artistName": "Mosaic S.r.l.",
      "kind": "Business",
      "releaseDate": "2013-01-21T16:27:56-07:00",
      "artworkUrl100": "https://is1-ssl.mzstatic.com/image/thumb/Purple211/v4/bc/18/a1/bc18a138-56ed-e6de-5ecb-0ca7b90fec10/AppIcon-0-0-1x_U007emarketing-0-2-0-sRGB-85-220.png/100x100bb.png",
      "url": ""
    },
    {
      "date": "2026-02-25",
      "rank": 8,
      "id": "335047649",
      "name": "ScanBizCards",
      "artistName": "ScanBiz Mobile Solutions L.P.",
      "kind": "Business",
      "releaseDate": "2009-10-28T13:15:08-07:00",
      "artworkUrl100": "https://is1-ssl.mzstatic.com/image/thumb/Purple221/v4/0e/b1/ef/0eb1ef3f-f72b-2b3c-c1a6-a0ee1ad4c497/AppIcon-0-0-1x_U007emarketing-0-7-0-85-220.png/100x100bb.png",
      "url": ""
    },
    {
      "date": "2026-02-25",
      "rank": 9,
      "id": "1212427529",
      "name": "WinFab - Sheet Metal Ductulator",
      "artistName": "pasquale dipaola",
      "kind": "Business",
      "releaseDate": "2017-03-08T09:02:30-07:00",
      "artworkUrl100": "https://is1-ssl.mzstatic.com/image/thumb/Purple111/v4/ce/0a/1c/ce0a1c95-4e1d-7e0b-d46b-df096a13d90e/pr_source.png/100x100bb.png",
      "url": ""
    },
    {
      "date": "2026-02-25",
      "rank": 10,
      "id": "734328438",
      "name": "Daughters of the King Daily De",
      "artistName": "Kesha Trippett",
      "kind": "Business",
      "releaseDate": "2013-11-04T15:37:51-07:00",
      "artworkUrl100": "https://is1-ssl.mzstatic.com/image/thumb/Purple221/v4/02/9b/ac/029bacb1-c8f1-8b62-6cad-ef1e375f40ae/AppIcon-0-0-1x_U007emarketing-0-0-0-8-0-0-sRGB-0-0-0-GLES2_U002c0-512MB-85-220-0-0.png/100x100bb.png",
      "url": ""
    },
    {
      "date": "2026-02-25",
      "rank": 11,
      "id": "1135811739",
      "name": "FAX from iPhone & iPad App",
      "artistName": "BPMobile",
      "kind": "Business",
      "releaseDate": "2016-09-01T18:59:02-07:00",
      "artworkUrl100": "https://is1-ssl.mzstatic.com/image/thumb/Purple211/v4/53/d9/88/53d988a4-2532-20dc-f1b7-f6ef1eca9420/AppIcon-1x_U007emarketing-0-7-0-85-220.jpeg/100x100bb.png",
      "url": ""
    },
    {
      "date": "2026-02-25",
      "rank": 12,
      "id": "854618029",
      "name": "FileBrowser Professional",
      "artistName": "Stratospherix Ltd",
      "kind": "Business",
      "releaseDate": "2014-04-17T21:18:48-07:00",
      "artworkUrl100": "https://is1-ssl.mzstatic.com/image/thumb/Purple211/v4/d8/e7/08/d8e708ae-7651-a2e9-bb73-3ddc6a5307d2/AppIcon-0-0-1x_U007epad-0-1-85-220.png/100x100bb.png",
      "url": "https://apps.apple.com/us/app/filebrowser-professional/id854618029?uo=2"
    },
    {
      "date": "2026-02-25",
      "rank": 13,
      "id": "412366083",
      "name": "CameraVision",
      "artistName": "Masayuki Akamatsu",
      "kind": "Business",
      "releaseDate": "2011-01-03T13:55:37-07:00",
      "artworkUrl100": "https://is1-ssl.mzstatic.com/image/thumb/Purple221/v4/34/ea/ed/34eaed73-aabb-f3a9-86be-6d83a412f599/AppIcon-0-0-1x_U007epad-0-1-0-0-85-220.png/100x100bb.png",
      "url": ""
    },
    {
      "date": "2026-02-25",
      "rank": 14,
      "id": "389226881",
      "name": "KoolerIce",
      "artistName": "Prism Systems, Inc.",
      "kind": "Business",
      "releaseDate": "2010-09-02T08:12:54-07:00",
      "artworkUrl100": "https://is1-ssl.mzstatic.com/image/thumb/Purple116/v4/01/38/9e/01389e4c-57b9-47a1-542a-02354a8be6bb/AppIcons-0-1x_U007emarketing-0-7-0-85-220.png/100x100bb.png",
      "url": ""
    },
    {
      "date": "2026-02-25",
      "rank": 15,
      "id": "522627917",
      "name": "FTPManager Pro",
      "artistName": "Skyjos Co., Ltd.",
      "kind": "Business",
      "releaseDate": "2012-05-03T08:30:36-07:00",
      "artworkUrl100": "https://is1-ssl.mzstatic.com/image/thumb/Purple211/v4/13/28/41/13284184-66ca-143e-a51b-9d4d97891b07/FTPManagerAppIcon-0-0-1x_U007epad-0-1-0-85-220.png/100x100bb.png",
      "url": "https://apps.apple.com/us/app/ftpmanager-pro/id522627917?uo=2"
    },
    {
      "date": "2026-02-25",
      "rank": 16,
      "id": "1447325991",
      "name": "FaxCover - Fax Cover Sheet",
      "artistName": "Actual Software Inc.",
      "kind": "Business",
      "releaseDate": "2021-01-14T00:00:00-07:00",
      "artworkUrl100": "https://is1-ssl.mzstatic.com/image/thumb/Purple124/v4/d8/0d/06/d80d060b-20f7-7bca-d983-e78e6a929a82/AppIcon-0-0-1x_U007emarketing-0-0-0-7-0-0-sRGB-0-0-0-GLES2_U002c0-512MB-85-220-0-0.png/100x100bb.png",
      "url": ""
    },
    {
      "date": "2026-02-25",
      "rank": 17,
      "id": "6751245004",
      "name": "Cold Call X",
      "artistName": "Vadym Berberian",
      "kind": "Business",
      "releaseDate": "2025-09-04T00:00:00-07:00",
      "artworkUrl100": "https://is1-ssl.mzstatic.com/image/thumb/Purple211/v4/c3/ac/06/c3ac0682-8faa-daae-946a-36a2f51be41b/AppIcon-0-0-1x_U007emarketing-0-11-0-85-220.png/100x100bb.png",
      "url": "https://apps.apple.com/us/app/cold-call-x/id6751245004?uo=2"
    },
    {
      "date": "2026-02-25",
      "rank": 18,
      "id": "307868751",
      "name": "JotNot Scanner App Pro",
      "artistName": "MobiTech 3000 LLC",
      "kind": "Business",
      "releaseDate": "2009-03-26T19:06:34-07:00",
      "artworkUrl100": "https://is1-ssl.mzstatic.com/image/thumb/Purple124/v4/7a/2a/ba/7a2abab1-e2b0-d867-e421-e471d3a54ba1/AppIcon-0-0-1x_U007emarketing-0-0-0-7-0-0-sRGB-0-0-0-GLES2_U002c0-512MB-85-220-0-0.png/100x100bb.png",
      "url": ""
    },
    {
      "date": "2026-02-25",
      "rank": 19,
      "id": "1357933382",
      "name": "BlindsBook Drapery Calculator",
      "artistName": "BlindsBook Corp",
      "kind": "Business",
      "releaseDate": "2018-03-14T10:11:25-07:00",
      "artworkUrl100": "https://is1-ssl.mzstatic.com/image/thumb/Purple211/v4/79/63/c6/7963c6de-a661-b84f-8830-4ece80278d91/AppIcon-0-0-1x_U007epad-0-1-85-220.png/100x100bb.png",
      "url": ""
    },
    {
      "date": "2026-02-25",
      "rank": 20,
      "id": "1095144176",
      "name": "ClearScanner Pro: PDF Scanning",
      "artistName": "INDY MOBILE APP COMPANY LIMITED",
      "kind": "Business",
      "releaseDate": "2016-03-25T16:33:11-07:00",
      "artworkUrl100": "https://is1-ssl.mzstatic.com/image/thumb/Purple211/v4/c8/4a/8e/c84a8e77-dbaa-3b25-901a-1b0a85f6550e/AppIcon-0-0-1x_U007epad-0-11-0-85-220.png/100x100bb.png",
      "url": ""
    },
    {
      "date": "2026-02-25",
      "rank": 21,
      "id": "867478383",
      "name": "Gamma Calculator Pro",
      "artistName": "Gerrit kleyn Winkel",
      "kind": "Business",
      "releaseDate": "2014-05-05T13:36:51-07:00",
      "artworkUrl100": "https://is1-ssl.mzstatic.com/image/thumb/Purple211/v4/15/62/c8/1562c8c9-e59c-7117-e949-c1be00f50a10/AppIcon-1x_U007emarketing-0-8-0-85-220-0.png/100x100bb.png",
      "url": ""
    },
    {
      "date": "2026-02-25",
      "rank": 22,
      "id": "480486428",
      "name": "Construction Cost Estimator",
      "artistName": "Wasatch Digital Media, Inc.",
      "kind": "Business",
      "releaseDate": "2012-07-05T07:40:46-07:00",
      "artworkUrl100": "https://is1-ssl.mzstatic.com/image/thumb/Purple126/v4/47/67/6b/47676b09-8d85-9503-38e5-fdf1de4b883e/AppIcon-0-0-1x_U007emarketing-0-0-0-5-0-0-sRGB-0-0-0-GLES2_U002c0-512MB-85-220-0-0.jpeg/100x100bb.png",
      "url": ""
    },
    {
      "date": "2026-02-25",
      "rank": 23,
      "id": "6746970166",
      "name": "Check Generator",
      "artistName": "Jason Hatzelis",
      "kind": "Business",
      "releaseDate": "2025-06-10T00:00:00-07:00",
      "artworkUrl100": "https://is1-ssl.mzstatic.com/image/thumb/Purple211/v4/31/57/3a/31573a12-255c-371f-0c24-a78f9af982a4/AppIcon-0-0-1x_U007ephone-0-1-85-220.png/100x100bb.png",
      "url": "https://apps.apple.com/us/app/check-generator/id6746970166?uo=2"
    },
    {
      "date": "2026-02-25",
      "rank": 24,
      "id": "425341262",
      "name": "FTP Client Pro",
      "artistName": "LessIsMore Development",
      "kind": "Business",
      "releaseDate": "2011-03-17T15:21:04-07:00",
      "artworkUrl100": "https://is1-ssl.mzstatic.com/image/thumb/Purple113/v4/2f/88/e8/2f88e8d3-fa8d-73a4-5bdc-8585955c131c/AppIcon-0-0-1x_U007emarketing-0-0-0-9-85-220.jpeg/100x100bb.png",
      "url": ""
    },
    {
      "date": "2026-02-25",
      "rank": 25,
      "id": "1084143351",
      "name": "Tap Forms Organizer 5 Database",
      "artistName": "Tap Zapp Software Inc.",
      "kind": "Business",
      "releaseDate": "2016-08-19T21:58:45-07:00",
      "artworkUrl100": "https://is1-ssl.mzstatic.com/image/thumb/Purple221/v4/e1/50/f3/e150f308-13f9-5224-2749-7d7873765992/AppIcon-0-1x_U007emarketing-0-8-0-85-220-0.png/100x100bb.png",
      "url": ""
    },
    {
      "date": "2026-02-25",
      "rank": 26,
      "id": "774662043",
      "name": "Quick2257",
      "artistName": "Lawrence Walters",
      "kind": "Business",
      "releaseDate": "2013-12-09T19:04:47-07:00",
      "artworkUrl100": "https://is1-ssl.mzstatic.com/image/thumb/Purple126/v4/3b/65/5a/3b655a70-ac4f-7c1e-f42a-248e37bec0f4/AppIcon-1x_U007emarketing-0-7-0-85-220.png/100x100bb.png",
      "url": ""
    },
    {
      "date": "2026-02-25",
      "rank": 27,
      "id": "992941305",
      "name": "Mud Engineer",
      "artistName": "bader alshammari",
      "kind": "Business",
      "releaseDate": "2015-05-30T03:14:59-07:00",
      "artworkUrl100": "https://is1-ssl.mzstatic.com/image/thumb/Purple116/v4/22/19/95/22199505-3437-c48a-8bf5-fd65b5df4216/AppIcon-0-0-1x_U007emarketing-0-0-0-7-0-0-sRGB-0-0-0-GLES2_U002c0-512MB-85-220-0-0.png/100x100bb.png",
      "url": ""
    },
    {
      "date": "2026-02-25",
      "rank": 28,
      "id": "1519099937",
      "name": "PDF Office Pro, Acrobat Expert",
      "artistName": "heytopia",
      "kind": "Business",
      "releaseDate": "2020-09-16T00:00:00-07:00",
      "artworkUrl100": "https://is1-ssl.mzstatic.com/image/thumb/Purple116/v4/84/3a/11/843a11e3-534e-91a4-1006-0b3c13e9a222/AppIcon_PDFiOS-0-1x_U007emarketing-0-7-0-85-220.png/100x100bb.png",
      "url": ""
    },
    {
      "date": "2026-02-25",
      "rank": 29,
      "id": "289968941",
      "name": "Network Ping",
      "artistName": "MochaSoft",
      "kind": "Business",
      "releaseDate": "2019-02-13T00:00:00-07:00",
      "artworkUrl100": "https://is1-ssl.mzstatic.com/image/thumb/Purple221/v4/49/22/58/492258f6-a0cf-4e46-bbca-f3776f00aef8/AppIcon-0-0-1x_U007emarketing-0-7-0-85-220.png/100x100bb.png",
      "url": "https://apps.apple.com/us/app/network-ping/id289968941?uo=2"
    },
    {
      "date": "2026-02-25",
      "rank": 30,
      "id": "522706442",
      "name": "Sync Folders Pro",
      "artistName": "VADIM ZYBIN",
      "kind": "Business",
      "releaseDate": "2012-05-16T14:18:47-07:00",
      "artworkUrl100": "https://is1-ssl.mzstatic.com/image/thumb/Purple126/v4/c3/b5/41/c3b541a5-8a55-7fb5-408c-39b23a2871d9/AppIcon-1x_U007emarketing-0-7-0-P3-85-220.png/100x100bb.png",
      "url": ""
    },
    {
      "date": "2026-02-25",
      "rank": 31,
      "id": "1567674162",
      "name": "Drink Cost PRO",
      "artistName": "Maurizio Polverini",
      "kind": "Business",
      "releaseDate": "2021-05-16T00:00:00-07:00",
      "artworkUrl100": "https://is1-ssl.mzstatic.com/image/thumb/Purple125/v4/bb/6b/45/bb6b45c9-8921-af5e-5894-ec56aa5b57d9/AppIcon-BuildServer-0-0-1x_U007emarketing-0-0-0-10-0-0-sRGB-0-0-0-GLES2_U002c0-512MB-85-220-0-0.png/100x100bb.png",
      "url": ""
    },
    {
      "date": "2026-02-25",
      "rank": 32,
      "id": "6742566060",
      "name": "DocCompare: PDF & Word Diff",
      "artistName": "EMRE KOTUN",
      "kind": "Business",
      "releaseDate": "2025-02-27T00:00:00-07:00",
      "artworkUrl100": "https://is1-ssl.mzstatic.com/image/thumb/Purple221/v4/71/2f/ae/712fae26-df20-99b3-6466-469d60bcecf7/AppIcon-0-0-1x_U007emarketing-0-11-0-85-220.png/100x100bb.png",
      "url": "https://apps.apple.com/us/app/doccompare-pdf-word-diff/id6742566060?uo=2"
    },
    {
      "date": "2026-02-25",
      "rank": 33,
      "id": "288362053",
      "name": "Remote Desktop - RDP",
      "artistName": "MochaSoft",
      "kind": "Business",
      "releaseDate": "2019-02-12T00:00:00-07:00",
      "artworkUrl100": "https://is1-ssl.mzstatic.com/image/thumb/Purple221/v4/23/8f/e1/238fe1a3-1d96-c23d-3335-e363b5ac5882/AppIcon-0-0-1x_U007emarketing-0-6-0-85-220.png/100x100bb.png",
      "url": ""
    },
    {
      "date": "2026-02-25",
      "rank": 34,
      "id": "1554333435",
      "name": "ITI Calc",
      "artistName": "Calculated Industries",
      "kind": "Business",
      "releaseDate": "2021-03-24T00:00:00-07:00",
      "artworkUrl100": "https://is1-ssl.mzstatic.com/image/thumb/Purple114/v4/71/a3/09/71a309a1-ba0c-c098-8ee2-539eb93243be/AppIcon4186-0-0-1x_U007emarketing-0-0-0-7-0-0-sRGB-0-0-0-GLES2_U002c0-512MB-85-220-0-0.png/100x100bb.png",
      "url": ""
    },
    {
      "date": "2026-02-25",
      "rank": 35,
      "id": "699434089",
      "name": "QuickPlan - Project Gantt Plan",
      "artistName": "皓 李",
      "kind": "Business",
      "releaseDate": "2013-10-20T06:11:27-07:00",
      "artworkUrl100": "https://is1-ssl.mzstatic.com/image/thumb/Purple211/v4/6a/d8/ab/6ad8ab5b-5bb2-56d7-1520-2643083403d6/AppIcons-0-0-1x_U007emarketing-0-8-0-sRGB-85-220.png/100x100bb.png",
      "url": ""
    },
    {
      "date": "2026-02-25",
      "rank": 36,
      "id": "1119117405",
      "name": "SketchCut PRO",
      "artistName": "Vladimir Rudenko",
      "kind": "Business",
      "releaseDate": "2016-06-14T12:06:44-07:00",
      "artworkUrl100": "https://is1-ssl.mzstatic.com/image/thumb/Purple116/v4/0c/ef/01/0cef01e3-42dc-ad1e-eae8-8ad4e36b4e6a/AppIcon-0-0-1x_U007emarketing-0-0-0-7-0-0-sRGB-0-0-0-GLES2_U002c0-512MB-85-220-0-0.png/100x100bb.png",
      "url": ""
    },
    {
      "date": "2026-02-25",
      "rank": 37,
      "id": "345667703",
      "name": "STX",
      "artistName": "Salon Transcripts, Inc.",
      "kind": "Business",
      "releaseDate": "2009-12-17T12:20:58-07:00",
      "artworkUrl100": "https://is1-ssl.mzstatic.com/image/thumb/Purple123/v4/b0/31/ff/b031ff82-eef3-5789-8556-25baf60f6602/AppIcon-1x_U007emarketing-0-7-0-85-220.png/100x100bb.png",
      "url": ""
    },
    {
      "date": "2026-02-25",
      "rank": 38,
      "id": "531272886",
      "name": "ICRSS PRO",
      "artistName": "ICRealtime LLC",
      "kind": "Business",
      "releaseDate": "2012-06-05T16:45:06-07:00",
      "artworkUrl100": "https://is1-ssl.mzstatic.com/image/thumb/Purple112/v4/45/67/1c/45671cf0-5968-54e9-f2d5-90ecf3905c42/AppIcon-1x_U007emarketing-0-7-0-sRGB-85-220.png/100x100bb.png",
      "url": ""
    },
    {
      "date": "2026-02-25",
      "rank": 39,
      "id": "438623352",
      "name": "Mastering the 48 Laws of Power",
      "artistName": "Adaptive Mentoring Systems Inc.",
      "kind": "Business",
      "releaseDate": "2011-05-30T00:00:00-07:00",
      "artworkUrl100": "https://is1-ssl.mzstatic.com/image/thumb/Purple128/v4/d5/28/76/d52876de-c3e2-5904-7ed4-43ba1a2e2675/AppIcon-1x_U007emarketing-0-0-GLES2_U002c0-512MB-sRGB-0-0-0-85-220-0-0-0-6.png/100x100bb.png",
      "url": ""
    },
    {
      "date": "2026-02-25",
      "rank": 40,
      "id": "1319538118",
      "name": "HTML Email Signature - Mail",
      "artistName": "Element26, Inc.",
      "kind": "Business",
      "releaseDate": "2017-12-03T11:03:07-07:00",
      "artworkUrl100": "https://is1-ssl.mzstatic.com/image/thumb/Purple126/v4/4a/92/ac/4a92acd4-534a-9fe4-1e97-e34776af814d/AppIcon-1x_U007emarketing-0-7-0-0-85-220-0.png/100x100bb.png",
      "url": ""
    },
    {
      "date": "2026-02-25",
      "rank": 41,
      "id": "456984826",
      "name": "Contact Mover",
      "artistName": "Immense Networks",
      "kind": "Business",
      "releaseDate": "2011-08-22T11:11:40-07:00",
      "artworkUrl100": "https://is1-ssl.mzstatic.com/image/thumb/Purple62/v4/e3/74/33/e37433ca-60da-eeb4-941b-c3a78bf368f9/mzl.wtyxweam.png/100x100bb.png",
      "url": ""
    },
    {
      "date": "2026-02-25",
      "rank": 42,
      "id": "489413229",
      "name": "TouchTax",
      "artistName": "Matthias Edrich",
      "kind": "Business",
      "releaseDate": "2011-12-16T20:32:13-07:00",
      "artworkUrl100": "https://is1-ssl.mzstatic.com/image/thumb/Purple211/v4/ab/8f/0f/ab8f0f17-6c7c-201a-dd67-35cbe6eb4d8d/AppIcon-0-0-1x_U007emarketing-0-8-0-85-220.png/100x100bb.png",
      "url": ""
    },
    {
      "date": "2026-02-25",
      "rank": 43,
      "id": "1446738885",
      "name": "Kiosker Pro: Web Kiosk",
      "artistName": "Top North AB",
      "kind": "Business",
      "releaseDate": "2019-08-25T10:01:32-07:00",
      "artworkUrl100": "https://is1-ssl.mzstatic.com/image/thumb/Purple211/v4/34/6d/2e/346d2e3e-970f-d81d-3617-a7f2fa64d272/ProIcon-0-0-1x_U007epad-0-1-85-220.png/100x100bb.png",
      "url": ""
    },
    {
      "date": "2026-02-25",
      "rank": 44,
      "id": "1285025662",
      "name": "SwiftDocs: PDF Document Maker",
      "artistName": "The Basic Software Company",
      "kind": "Business",
      "releaseDate": "2017-09-22T04:07:00-07:00",
      "artworkUrl100": "https://is1-ssl.mzstatic.com/image/thumb/Purple211/v4/3e/99/71/3e997146-cb4a-890b-466a-0c01a70169e2/AppIcon-0-0-1x_U007emarketing-0-7-0-85-220.png/100x100bb.png",
      "url": ""
    },
    {
      "date": "2026-02-25",
      "rank": 45,
      "id": "1666371152",
      "name": "Wandy Numerología",
      "artistName": "Joan Tejada",
      "kind": "Business",
      "releaseDate": "2023-02-23T00:00:00-07:00",
      "artworkUrl100": "https://is1-ssl.mzstatic.com/image/thumb/Purple221/v4/37/30/bc/3730bc99-6a15-d918-a6e9-d5382d66aeb1/AppIcon-0-0-1x_U007emarketing-0-8-0-85-220.png/100x100bb.png",
      "url": ""
    },
    {
      "date": "2026-02-25",
      "rank": 46,
      "id": "1189800077",
      "name": "business card scanner : reader",
      "artistName": "Sounak Sarkar",
      "kind": "Business",
      "releaseDate": "2017-01-05T09:24:11-07:00",
      "artworkUrl100": "https://is1-ssl.mzstatic.com/image/thumb/Purple126/v4/f8/73/48/f8734896-9ac8-d113-1b39-19e5f1cc102a/AppIcon-0-0-1x_U007emarketing-0-7-0-85-220.jpeg/100x100bb.png",
      "url": ""
    },
    {
      "date": "2026-02-25",
      "rank": 47,
      "id": "515747232",
      "name": "BlasToolsPro",
      "artistName": "Pavel Popov Consulting Inc.",
      "kind": "Business",
      "releaseDate": "2012-04-06T18:09:25-07:00",
      "artworkUrl100": "https://is1-ssl.mzstatic.com/image/thumb/Purple211/v4/8b/64/16/8b641673-b7ab-af77-c87d-82d1f9f88007/AppIcon-0-0-1x_U007emarketing-0-7-0-85-220.png/100x100bb.png",
      "url": ""
    },
    {
      "date": "2026-02-25",
      "rank": 48,
      "id": "6748548925",
      "name": "Smart Auto Loan Calculator",
      "artistName": "Gabriel Jaquier",
      "kind": "Business",
      "releaseDate": "2025-07-21T00:00:00-07:00",
      "artworkUrl100": "https://is1-ssl.mzstatic.com/image/thumb/Purple221/v4/a9/ee/de/a9eede3a-87a9-ccf8-6345-21faedac5c7b/AppIcon-0-0-1x_U007epad-0-1-85-220.png/100x100bb.png",
      "url": "https://apps.apple.com/us/app/smart-auto-loan-calculator/id6748548925?uo=2"
    },
    {
      "date": "2026-02-25",
      "rank": 49,
      "id": "1474083420",
      "name": "ezModbus",
      "artistName": "Bitmakers LLC",
      "kind": "Business",
      "releaseDate": "2019-08-06T00:00:00-07:00",
      "artworkUrl100": "https://is1-ssl.mzstatic.com/image/thumb/Purple112/v4/6c/0d/33/6c0d3398-f459-a874-aa66-afd27ff61554/AppIcon-1x_U007emarketing-0-7-0-85-220.png/100x100bb.png",
      "url": ""
    },
    {
      "date": "2026-02-25",
      "rank": 50,
      "id": "6743338083",
      "name": "Share a Contact",
      "artistName": "Jesse Vincent",
      "kind": "Business",
      "releaseDate": "2025-04-01T00:00:00-07:00",
      "artworkUrl100": "https://is1-ssl.mzstatic.com/image/thumb/Purple211/v4/72/2f/d3/722fd35f-7e1f-2bff-6fa2-82236aa4daba/AppIcon-1x_U007emarketing-0-8-0-85-220-0.png/100x100bb.png",
      "url": "https://apps.apple.com/us/app/share-a-contact/id6743338083?uo=2"
    },
    {
      "date": "2026-02-25",
      "rank": 51,
      "id": "6749387770",
      "name": "Email Address Extractor Pro",
      "artistName": "Fenuku Kekeli",
      "kind": "Business",
      "releaseDate": "2025-08-06T00:00:00-07:00",
      "artworkUrl100": "https://is1-ssl.mzstatic.com/image/thumb/Purple211/v4/e5/59/97/e5599776-db1b-aae5-b6f8-59c8d3a1d6fd/AppIcon-0-0-1x_U007epad-0-1-85-220.png/100x100bb.png",
      "url": "https://apps.apple.com/us/app/email-address-extractor-pro/id6749387770?uo=2"
    },
    {
      "date": "2026-02-25",
      "rank": 52,
      "id": "6759301468",
      "name": "DocuSCAN 2026",
      "artistName": "Razvan IVAN",
      "kind": "Business",
      "releaseDate": "2026-02-24T07:28:16-07:00",
      "artworkUrl100": "https://is1-ssl.mzstatic.com/image/thumb/Purple221/v4/cc/65/f8/cc65f8f8-6f0e-8a71-cd58-f928b2b3b9c6/AppIcon-0-0-1x_U007epad-0-1-85-220.png/100x100bb.png",
      "url": "https://apps.apple.com/us/app/docuscan-2026/id6759301468?uo=2"
    },
    {
      "date": "2026-02-25",
      "rank": 53,
      "id": "1556128361",
      "name": "SoftToken",
      "artistName": "David Southgate",
      "kind": "Business",
      "releaseDate": "2021-03-31T00:00:00-07:00",
      "artworkUrl100": "https://is1-ssl.mzstatic.com/image/thumb/Purple126/v4/aa/46/1b/aa461b03-ca33-84c7-c10a-53ed5861b3d2/AppIcon-0-0-1x_U007emarketing-0-7-0-85-220.png/100x100bb.png",
      "url": ""
    },
    {
      "date": "2026-02-25",
      "rank": 54,
      "id": "391312617",
      "name": "Profit Story",
      "artistName": "VooZu Promotions LLC",
      "kind": "Business",
      "releaseDate": "2010-11-16T12:01:20-07:00",
      "artworkUrl100": "https://is1-ssl.mzstatic.com/image/thumb/Purple3/v4/12/0e/88/120e88da-e067-78e3-3a43-629e7f568b3a/mzl.jnimiqri.jpg/100x100bb.png",
      "url": ""
    },
    {
      "date": "2026-02-25",
      "rank": 55,
      "id": "401818935",
      "name": "Genius Scan Enterprise - PDF",
      "artistName": "The Grizzly Labs",
      "kind": "Business",
      "releaseDate": "2010-12-15T20:48:12-07:00",
      "artworkUrl100": "https://is1-ssl.mzstatic.com/image/thumb/Purple221/v4/25/bb/09/25bb09ff-b0ea-e5a7-9c8a-852c972a4d37/AppIcon-0-0-1x_U007epad-0-1-sRGB-85-220.png/100x100bb.png",
      "url": "https://apps.apple.com/us/app/genius-scan-enterprise-pdf/id401818935?uo=2"
    },
    {
      "date": "2026-02-25",
      "rank": 56,
      "id": "908554933",
      "name": "Flood Zone Map",
      "artistName": "Ikonetics",
      "kind": "Business",
      "releaseDate": "2014-10-13T22:47:53-07:00",
      "artworkUrl100": "https://is1-ssl.mzstatic.com/image/thumb/Purple211/v4/17/ab/00/17ab00a8-212d-2f9c-867e-813ccdef52e0/AppIcon-0-0-1x_U007emarketing-0-8-0-85-220.png/100x100bb.png",
      "url": ""
    },
    {
      "date": "2026-02-25",
      "rank": 57,
      "id": "285877935",
      "name": "QuickVoice2Text Email (PRO Recorder)",
      "artistName": "nFinity Inc",
      "kind": "Business",
      "releaseDate": "2019-01-31T00:00:00-07:00",
      "artworkUrl100": "https://is1-ssl.mzstatic.com/image/thumb/Purple60/v4/b5/5e/55/b55e551d-23c4-f5ba-e929-27fef331c4db/mzm.axcvdtaf.png/100x100bb.png",
      "url": ""
    },
    {
      "date": "2026-02-25",
      "rank": 58,
      "id": "1617910987",
      "name": "Countertops Draw",
      "artistName": "Simple App Solutions",
      "kind": "Business",
      "releaseDate": "2022-04-21T00:00:00-07:00",
      "artworkUrl100": "https://is1-ssl.mzstatic.com/image/thumb/Purple112/v4/07/f7/03/07f70391-93c9-72b0-c999-9a3490d0b2a2/AppIcon-0-0-1x_U007emarketing-0-0-0-7-0-0-sRGB-0-0-0-GLES2_U002c0-512MB-85-220-0-0.png/100x100bb.png",
      "url": ""
    },
    {
      "date": "2026-02-25",
      "rank": 59,
      "id": "953739548",
      "name": "Contacts2XL",
      "artistName": "Technomagination, LLC",
      "kind": "Business",
      "releaseDate": "2016-05-05T11:49:13-07:00",
      "artworkUrl100": "https://is1-ssl.mzstatic.com/image/thumb/Purple221/v4/7a/53/01/7a5301d7-3645-24f9-ca6f-5eca94d11e12/AppIcon-0-0-1x_U007epad-0-1-85-220.png/100x100bb.png",
      "url": "https://apps.apple.com/us/app/contacts2xl/id953739548?uo=2"
    },
    {
      "date": "2026-02-25",
      "rank": 60,
      "id": "1524363807",
      "name": "SwingSound Golf",
      "artistName": "Marius Filmalter",
      "kind": "Business",
      "releaseDate": "2020-08-27T00:00:00-07:00",
      "artworkUrl100": "https://is1-ssl.mzstatic.com/image/thumb/Purple122/v4/e9/ce/f2/e9cef2a2-96cc-6471-0894-5f083626b818/AppIcon-0-0-1x_U007emarketing-0-0-0-7-0-0-sRGB-0-0-0-GLES2_U002c0-512MB-85-220-0-0.png/100x100bb.png",
      "url": ""
    },
    {
      "date": "2026-02-25",
      "rank": 61,
      "id": "892393815",
      "name": "Awesome Voice Recorder PRO AVR",
      "artistName": "Newkline Co., Ltd.",
      "kind": "Business",
      "releaseDate": "2014-07-05T23:14:03-07:00",
      "artworkUrl100": "https://is1-ssl.mzstatic.com/image/thumb/Purple221/v4/f9/a2/aa/f9a2aa8e-9bbf-e29f-09f8-17b5b6b3055a/AppIcon_PRO-1x_U007epad-0-1-0-85-220-0.png/100x100bb.png",
      "url": ""
    },
    {
      "date": "2026-02-25",
      "rank": 62,
      "id": "703201018",
      "name": "Activate Your Voice",
      "artistName": "Elaine Clark",
      "kind": "Business",
      "releaseDate": "2013-10-02T00:00:00-07:00",
      "artworkUrl100": "https://is1-ssl.mzstatic.com/image/thumb/Purple221/v4/3c/8a/aa/3c8aaa67-e04b-2563-3e78-5ebe22658e61/AppIcon-1x_U007emarketing-0-11-0-0-85-220-0.png/100x100bb.png",
      "url": ""
    },
    {
      "date": "2026-02-25",
      "rank": 63,
      "id": "6749251675",
      "name": "ResDemand",
      "artistName": "John Stacy",
      "kind": "Business",
      "releaseDate": "2025-08-01T00:00:00-07:00",
      "artworkUrl100": "https://is1-ssl.mzstatic.com/image/thumb/Purple211/v4/5e/de/f4/5edef49b-6ba4-f35e-805b-d31c64a97980/AppIcon-0-0-1x_U007emarketing-0-11-0-85-220.png/100x100bb.png",
      "url": "https://apps.apple.com/us/app/resdemand/id6749251675?uo=2"
    },
    {
      "date": "2026-02-25",
      "rank": 64,
      "id": "608985698",
      "name": "VesselFinder Pro",
      "artistName": "AstraPaging Ltd.",
      "kind": "Business",
      "releaseDate": "2013-03-05T11:27:10-07:00",
      "artworkUrl100": "https://is1-ssl.mzstatic.com/image/thumb/Purple221/v4/15/fd/ce/15fdce41-be65-f719-e830-acd6abdcbe2f/AppIcon-0-0-1x_U007epad-0-1-85-220.png/100x100bb.png",
      "url": ""
    },
    {
      "date": "2026-02-25",
      "rank": 65,
      "id": "468090416",
      "name": "business card scanner-sam pro",
      "artistName": "娜 林",
      "kind": "Business",
      "releaseDate": "2011-09-30T15:43:33-07:00",
      "artworkUrl100": "https://is1-ssl.mzstatic.com/image/thumb/Purple125/v4/f2/57/dc/f257dcd7-6cbb-327c-34b6-5b0d955ead48/AppIcon_samCArdEuPro-0-1x_U007emarketing-0-5-0-0-85-220.png/100x100bb.png",
      "url": ""
    },
    {
      "date": "2026-02-25",
      "rank": 66,
      "id": "353431586",
      "name": "BizXpenseTracker",
      "artistName": "Silverware Software, LLC",
      "kind": "Business",
      "releaseDate": "2010-02-03T13:56:45-07:00",
      "artworkUrl100": "https://is1-ssl.mzstatic.com/image/thumb/Purple125/v4/1d/40/e3/1d40e3ba-d1de-2c1b-eb92-318efb6218cf/AppIconBXT-0-0-1x_U007emarketing-0-0-0-10-0-0-sRGB-0-0-0-GLES2_U002c0-512MB-85-220-0-0.png/100x100bb.png",
      "url": ""
    },
    {
      "date": "2026-02-25",
      "rank": 67,
      "id": "1585551136",
      "name": "Candle Calculator: Cost,Weight",
      "artistName": "Payal Seth",
      "kind": "Business",
      "releaseDate": "2021-09-16T00:00:00-07:00",
      "artworkUrl100": "https://is1-ssl.mzstatic.com/image/thumb/Purple116/v4/af/11/ca/af11ca15-b36b-a78b-e313-de09dfd13fd0/AppIcon-1x_U007emarketing-0-7-0-sRGB-85-220.png/100x100bb.png",
      "url": ""
    },
    {
      "date": "2026-02-25",
      "rank": 68,
      "id": "314525743",
      "name": "Visualize Success with AJ",
      "artistName": "Universal Relaxation Ltd",
      "kind": "Business",
      "releaseDate": "2009-05-06T14:48:10-07:00",
      "artworkUrl100": "https://is1-ssl.mzstatic.com/image/thumb/Purple116/v4/68/ab/a8/68aba811-f48a-a6f9-cade-5e03355125ea/contsched.lauibtni.png/100x100bb.png",
      "url": ""
    },
    {
      "date": "2026-02-25",
      "rank": 69,
      "id": "688640127",
      "name": "Easy Hours",
      "artistName": "30xi LLC",
      "kind": "Business",
      "releaseDate": "2013-08-20T13:16:18-07:00",
      "artworkUrl100": "https://is1-ssl.mzstatic.com/image/thumb/Purple113/v4/58/8e/98/588e98fe-decf-bfb1-a8c4-f94c96ca96f4/AppIcon-0-0-1x_U007emarketing-0-0-0-7-0-0-sRGB-0-0-0-GLES2_U002c0-512MB-85-220-0-0.png/100x100bb.png",
      "url": ""
    },
    {
      "date": "2026-02-25",
      "rank": 70,
      "id": "6443462145",
      "name": "Client Directory",
      "artistName": "Client-Data LLC",
      "kind": "Business",
      "releaseDate": "2022-10-25T00:00:00-07:00",
      "artworkUrl100": "https://is1-ssl.mzstatic.com/image/thumb/Purple116/v4/84/85/a8/8485a8ea-23e7-226e-c798-39e64d2f6d44/AppIcon-0-1x_U007ephone-85-220.png/100x100bb.png",
      "url": ""
    },
    {
      "date": "2026-02-25",
      "rank": 71,
      "id": "305014494",
      "name": "EZCalc Diamonds",
      "artistName": "ADIRsoft",
      "kind": "Business",
      "releaseDate": "2009-02-21T02:17:50-07:00",
      "artworkUrl100": "https://is1-ssl.mzstatic.com/image/thumb/Purple211/v4/0c/33/87/0c3387cd-b7f0-8228-5f31-d7dbdd733637/AppIcon-0-0-1x_U007epad-0-1-85-220.png/100x100bb.png",
      "url": "https://apps.apple.com/us/app/ezcalc-diamonds/id305014494?uo=2"
    },
    {
      "date": "2026-02-25",
      "rank": 72,
      "id": "538386564",
      "name": "VSD Viewer for Visio Drawings",
      "artistName": "Nektony LLC",
      "kind": "Business",
      "releaseDate": "2012-07-02T16:52:05-07:00",
      "artworkUrl100": "https://is1-ssl.mzstatic.com/image/thumb/Purple116/v4/22/cd/ba/22cdba3c-f629-e4a7-b1aa-ae4d20ca3f7e/AppIcon-0-0-1x_U007emarketing-0-0-0-7-0-0-sRGB-0-0-0-GLES2_U002c0-512MB-85-220-0-0.png/100x100bb.png",
      "url": ""
    },
    {
      "date": "2026-02-25",
      "rank": 73,
      "id": "683099193",
      "name": "Say&Go Voice Notes and Inbox",
      "artistName": "Dawid Pietrala",
      "kind": "Business",
      "releaseDate": "2013-08-15T00:00:00-07:00",
      "artworkUrl100": "https://is1-ssl.mzstatic.com/image/thumb/Purple113/v4/66/fb/54/66fb5411-4e91-fc4d-1b15-76874487507b/AppIcon-2-0-1x_U007emarketing-0-0-GLES2_U002c0-512MB-sRGB-0-0-0-85-220-0-0-0-8.png/100x100bb.png",
      "url": ""
    },
    {
      "date": "2026-02-25",
      "rank": 74,
      "id": "830782782",
      "name": "LawnCare Pro Invoicing & More",
      "artistName": "JZ Mobile LLC",
      "kind": "Business",
      "releaseDate": "2014-03-27T13:15:51-07:00",
      "artworkUrl100": "https://is1-ssl.mzstatic.com/image/thumb/Purple211/v4/94/80/54/94805470-e6aa-eb66-4b0a-9754c47ed2cb/AppIcon-0-1x_U007emarketing-0-4-0-sRGB-85-220-0.png/100x100bb.png",
      "url": ""
    },
    {
      "date": "2026-02-25",
      "rank": 75,
      "id": "789933121",
      "name": "SunLync Mobile Manager",
      "artistName": "SunLync",
      "kind": "Business",
      "releaseDate": "2014-01-07T12:53:01-07:00",
      "artworkUrl100": "https://is1-ssl.mzstatic.com/image/thumb/Purple118/v4/4b/98/b1/4b98b1dc-9264-e989-8e82-9fd72ae05649/AppIcon-0-1x_U007emarketing-0-0-GLES2_U002c0-512MB-sRGB-0-0-0-85-220-0-0-0-4.png/100x100bb.png",
      "url": ""
    },
    {
      "date": "2026-02-25",
      "rank": 76,
      "id": "861898768",
      "name": "Electrician Invoice & Estimate",
      "artistName": "JZ Mobile LLC",
      "kind": "Business",
      "releaseDate": "2014-04-18T13:35:30-07:00",
      "artworkUrl100": "https://is1-ssl.mzstatic.com/image/thumb/Purple211/v4/89/c0/ab/89c0ab33-6ddb-52db-16b6-3dfa8301394e/AppIcon-0-1x_U007emarketing-0-4-0-sRGB-85-220-0.png/100x100bb.png",
      "url": ""
    },
    {
      "date": "2026-02-25",
      "rank": 77,
      "id": "689788839",
      "name": "Rafter Tools+",
      "artistName": "Sim Ayers",
      "kind": "Business",
      "releaseDate": "2013-08-23T10:25:43-07:00",
      "artworkUrl100": "https://is1-ssl.mzstatic.com/image/thumb/Purple211/v4/ec/5e/d2/ec5ed24d-823a-159a-7b6a-c1709a8a0d79/AppIcon-1x_U007emarketing-0-10-0-85-220-0.png/100x100bb.png",
      "url": ""
    },
    {
      "date": "2026-02-25",
      "rank": 78,
      "id": "1619688401",
      "name": "Batch Mix",
      "artistName": "Stat Central LLC",
      "kind": "Business",
      "releaseDate": "2022-04-20T00:00:00-07:00",
      "artworkUrl100": "https://is1-ssl.mzstatic.com/image/thumb/Purple122/v4/0a/bb/f8/0abbf8d1-2196-99ab-cd6b-c2ff67f9d361/AppIcon-0-0-1x_U007emarketing-0-0-0-6-0-0-sRGB-0-0-0-GLES2_U002c0-512MB-85-220-0-0.png/100x100bb.png",
      "url": ""
    },
    {
      "date": "2026-02-25",
      "rank": 79,
      "id": "730873809",
      "name": "Job Sleuth",
      "artistName": "Hudson Ellis",
      "kind": "Business",
      "releaseDate": "2013-10-29T22:01:35-07:00",
      "artworkUrl100": "https://is1-ssl.mzstatic.com/image/thumb/Purple124/v4/25/2e/22/252e221f-dc1e-b956-5d62-5f99f30e0d2f/AppIcon-1x_U007emarketing-0-6-0-85-220.png/100x100bb.png",
      "url": ""
    },
    {
      "date": "2026-02-25",
      "rank": 80,
      "id": "445701154",
      "name": "Kiosk Pro Plus",
      "artistName": "Kiosk Group, Inc.",
      "kind": "Business",
      "releaseDate": "2011-10-14T13:01:03-07:00",
      "artworkUrl100": "https://is1-ssl.mzstatic.com/image/thumb/Purple211/v4/4c/e7/7a/4ce77a20-81a5-afea-f69c-bb33e61d4e00/AppIcon-1x_U007emarketing-0-11-0-0-85-220-0.png/100x100bb.png",
      "url": ""
    },
    {
      "date": "2026-02-25",
      "rank": 81,
      "id": "6450181489",
      "name": "AF Download Manager",
      "artistName": "Autoflame Engineering Ltd",
      "kind": "Business",
      "releaseDate": "2025-05-12T00:00:00-07:00",
      "artworkUrl100": "https://is1-ssl.mzstatic.com/image/thumb/Purple211/v4/f3/d1/5c/f3d15c1f-6edd-201c-96ea-c3e941b82724/AppIcon-0-0-1x_U007emarketing-0-11-0-85-220.png/100x100bb.png",
      "url": "https://apps.apple.com/us/app/af-download-manager/id6450181489?uo=2"
    },
    {
      "date": "2026-02-25",
      "rank": 82,
      "id": "1537313882",
      "name": "Contactless Business Card Pro",
      "artistName": "Khang Le",
      "kind": "Business",
      "releaseDate": "2020-10-25T00:00:00-07:00",
      "artworkUrl100": "https://is1-ssl.mzstatic.com/image/thumb/Purple211/v4/e1/c3/bc/e1c3bc13-555c-a230-8476-e7b9a917909b/AppIcon-0-0-1x_U007emarketing-0-8-0-85-220.png/100x100bb.png",
      "url": ""
    },
    {
      "date": "2026-02-25",
      "rank": 83,
      "id": "1199937929",
      "name": "eMariner",
      "artistName": "Mateo Kraljevic",
      "kind": "Business",
      "releaseDate": "2017-01-31T01:45:33-07:00",
      "artworkUrl100": "https://is1-ssl.mzstatic.com/image/thumb/Purple122/v4/fc/cb/6a/fccb6a1f-03c2-a2df-5509-b1b5ca4f222d/AppIcon-1x_U007emarketing-0-10-0-0-85-220-0.png/100x100bb.png",
      "url": ""
    },
    {
      "date": "2026-02-25",
      "rank": 84,
      "id": "1601559754",
      "name": "佛教经典歌曲大全",
      "artistName": "强 马",
      "kind": "Business",
      "releaseDate": "2021-12-22T00:00:00-07:00",
      "artworkUrl100": "https://is1-ssl.mzstatic.com/image/thumb/Purple211/v4/ad/d8/0b/add80b85-bf1e-3342-bf1e-661d01a5cf59/AppIcon-0-0-1x_U007emarketing-0-4-85-220.png/100x100bb.png",
      "url": ""
    },
    {
      "date": "2026-02-25",
      "rank": 85,
      "id": "6753956209",
      "name": "MixrPro Neat",
      "artistName": "ANDREW TURNBULL",
      "kind": "Business",
      "releaseDate": "2025-10-17T00:00:00-07:00",
      "artworkUrl100": "https://is1-ssl.mzstatic.com/image/thumb/Purple211/v4/25/ce/d5/25ced563-68fd-b21e-6f41-0da8702a5eb3/AppIcon-0-0-1x_U007epad-0-1-85-220.png/100x100bb.png",
      "url": "https://apps.apple.com/us/app/mixrpro-neat/id6753956209?uo=2"
    },
    {
      "date": "2026-02-25",
      "rank": 86,
      "id": "1641730648",
      "name": "Kanban Daily",
      "artistName": "Pavolle Bilisim Ticaret Limited Sirketi",
      "kind": "Business",
      "releaseDate": "2022-09-07T00:00:00-07:00",
      "artworkUrl100": "https://is1-ssl.mzstatic.com/image/thumb/Purple112/v4/93/fd/76/93fd764a-9fbb-6ac5-5585-fe2f1cef3367/AppIcon-1x_U007emarketing-0-7-85-220.png/100x100bb.png",
      "url": ""
    },
    {
      "date": "2026-02-25",
      "rank": 87,
      "id": "6757134058",
      "name": "My Certification Tracker",
      "artistName": "Skaggs Media LLC",
      "kind": "Business",
      "releaseDate": "2026-01-08T00:00:00-07:00",
      "artworkUrl100": "https://is1-ssl.mzstatic.com/image/thumb/Purple211/v4/e0/d1/1e/e0d11ece-e471-ab21-3e3b-7162a53c3e8f/AppIcon-0-0-1x_U007epad-0-1-85-220.png/100x100bb.png",
      "url": "https://apps.apple.com/us/app/my-certification-tracker/id6757134058?uo=2"
    },
    {
      "date": "2026-02-25",
      "rank": 88,
      "id": "6444574623",
      "name": "Libreoffice Viewer .",
      "artistName": "Aditya Wagh",
      "kind": "Business",
      "releaseDate": "2022-11-20T00:00:00-07:00",
      "artworkUrl100": "https://is1-ssl.mzstatic.com/image/thumb/Purple126/v4/76/c0/3d/76c03d9a-dcbe-6c25-431e-03bafdd1de04/AppIcon-0-0-1x_U007emarketing-0-0-0-7-0-0-sRGB-0-0-0-GLES2_U002c0-512MB-85-220-0-0.png/100x100bb.png",
      "url": ""
    },
    {
      "date": "2026-02-25",
      "rank": 89,
      "id": "338550388",
      "name": "Audio Memos",
      "artistName": "Imesart S.a.r.l.",
      "kind": "Business",
      "releaseDate": "2009-11-25T13:20:47-07:00",
      "artworkUrl100": "https://is1-ssl.mzstatic.com/image/thumb/Purple211/v4/96/9e/f7/969ef71b-3d4a-e37f-f0ae-06f3916548d6/Icon-0-0-1x_U007epad-0-0-0-1-0-0-sRGB-85-220.png/100x100bb.png",
      "url": ""
    },
    {
      "date": "2026-02-25",
      "rank": 90,
      "id": "427761719",
      "name": "PrintCentral Pro for iPhone",
      "artistName": "EuroSmartz Ltd",
      "kind": "Business",
      "releaseDate": "2011-04-13T17:00:42-07:00",
      "artworkUrl100": "https://is1-ssl.mzstatic.com/image/thumb/Purple221/v4/44/18/db/4418db60-e8c8-99be-345a-c89b9a6bd4e4/AppIcon-pclproa-0-0-1x_U007emarketing-0-6-85-220.png/100x100bb.png",
      "url": ""
    },
    {
      "date": "2026-02-25",
      "rank": 91,
      "id": "285750155",
      "name": "iRecorder Pro Audio Recorder",
      "artistName": "SIMPLETOUCH LLC",
      "kind": "Business",
      "releaseDate": "2019-02-12T00:00:00-07:00",
      "artworkUrl100": "https://is1-ssl.mzstatic.com/image/thumb/Purple113/v4/6e/8a/2a/6e8a2a40-642f-d0a3-da16-afdab1456662/AppIcon-0-1x_U007emarketing-0-0-GLES2_U002c0-512MB-sRGB-0-0-0-85-220-0-0-0-7.png/100x100bb.png",
      "url": ""
    },
    {
      "date": "2026-02-25",
      "rank": 92,
      "id": "288013812",
      "name": "TimeScroller - timezone helper",
      "artistName": "Terry Brett",
      "kind": "Business",
      "releaseDate": "2019-02-02T00:00:00-07:00",
      "artworkUrl100": "https://is1-ssl.mzstatic.com/image/thumb/Purple124/v4/8f/0e/57/8f0e5734-00bc-1611-3749-21213b07bef7/AppIcon-1x_U007emarketing-0-2-0-0-85-220.png/100x100bb.png",
      "url": ""
    },
    {
      "date": "2026-02-25",
      "rank": 93,
      "id": "1197930396",
      "name": "Nova Fax: Send fax from iPhone",
      "artistName": "Nova Mobile, Inc.",
      "kind": "Business",
      "releaseDate": "2017-03-02T21:54:05-07:00",
      "artworkUrl100": "https://is1-ssl.mzstatic.com/image/thumb/Purple211/v4/6a/35/8a/6a358a3a-f1a2-2545-4885-71d5dae8cb42/AppIcon_1-0-0-1x_U007emarketing-0-8-0-sRGB-85-220.png/100x100bb.png",
      "url": ""
    },
    {
      "date": "2026-02-25",
      "rank": 94,
      "id": "1452061743",
      "name": "OpenDocument Reader Pro",
      "artistName": "Stefl und Taschauer OG",
      "kind": "Business",
      "releaseDate": "2019-02-15T03:36:03-07:00",
      "artworkUrl100": "https://is1-ssl.mzstatic.com/image/thumb/Purple211/v4/19/fb/1d/19fb1d0d-b23d-7dfe-b1fe-80c2b672c0cf/AppIcon-0-0-1x_U007emarketing-0-11-0-85-220.png/100x100bb.png",
      "url": ""
    },
    {
      "date": "2026-02-25",
      "rank": 95,
      "id": "6744589481",
      "name": "Chicken Planner",
      "artistName": "H3 Apps, LLC",
      "kind": "Business",
      "releaseDate": "2025-04-24T00:00:00-07:00",
      "artworkUrl100": "https://is1-ssl.mzstatic.com/image/thumb/Purple221/v4/1c/b1/e8/1cb1e884-047a-9325-5bee-e2e086fa0923/AppIcon-0-0-1x_U007epad-0-1-P3-85-220.png/100x100bb.png",
      "url": "https://apps.apple.com/us/app/chicken-planner/id6744589481?uo=2"
    },
    {
      "date": "2026-02-25",
      "rank": 96,
      "id": "468424673",
      "name": "Contacts Map: territory manage",
      "artistName": "Youngwan Choi",
      "kind": "Business",
      "releaseDate": "2011-10-03T23:57:02-07:00",
      "artworkUrl100": "https://is1-ssl.mzstatic.com/image/thumb/Purple211/v4/2d/9c/0f/2d9c0f23-99d8-dcd4-17e1-7f268ae12879/App-0-0-1x_U007epad-0-1-0-85-220.png/100x100bb.png",
      "url": ""
    },
    {
      "date": "2026-02-25",
      "rank": 97,
      "id": "728898059",
      "name": "MS SHIFT",
      "artistName": "Ori Zur",
      "kind": "Business",
      "releaseDate": "2014-01-13T13:03:07-07:00",
      "artworkUrl100": "https://is1-ssl.mzstatic.com/image/thumb/Purple125/v4/1e/c6/9b/1ec69b7a-6b64-dfae-768d-2c64ff4c148e/AppIcon-0-0-1x_U007emarketing-0-0-0-6-0-0-sRGB-0-0-0-GLES2_U002c0-512MB-85-220-0-0.png/100x100bb.png",
      "url": ""
    }
  ]
}
